[
  {
    "id": "P001",
    "name": "Rahul Services",
    "img": "https://picsum.photos/200/200?dog",
    "services": ["electrical", "paing", "Acepair", "Tv machanic", " Fridge", "car wash", "cleaning"],
    "phone": "9876543210",
    "whatsapp": "9876543210",
    "googleMap": "https://maps.google.com/?q=23.456,87.123"
  },
  {
    "id": "P002",
    "name": "Suman Painter",
    "img": "images/suman.jpg",
    "services": ["painting", "electrical"],
    "phone": "9123456780",
    "whatsapp": "9123456780",
    "googleMap": "https://maps.google.com/?q=23.111,87.222"
  },
  {
    "id": "P003",
    "name": "Amit Plumber",
    "img": "images/amit.jpg",
    "services": ["plumbing", "gardening"],
    "phone": "9000000000",
    "whatsapp": "9000000000",
    "googleMap": "https://maps.google.com/?q=23.333,87.444"
  }
]
